Workbook

Sheet Member Information Base
F4: Date
B5: Business Member | C5: LOA | D5: Letter of Authority | E5: Yes | F5: 46288
A6: Category | B6: Business Information | C6: EGF | D6: Engagement Form | E6: Yes
A7: Client Name | B7: ='Airtable Data Sheet'!B2 | C7: PSA | D7: Profit Sharing Agreement | E7: Yes
A8: Business Industry
A9: ABN | B9: ='Airtable Data Sheet'!K2 | C9: MRIN | D9: ='Airtable Data Sheet'!A2
A10: Postal Address | B10: ='Airtable Data Sheet'!F2
B17: Total
A19: Contact Name | B19: John Caporaso | C19: Contact Name | E19: Contact 3
A20: Position | B20: Director | C20: Position | E20: Contact Number
A21: Number | B21: 0430 157 149 | C21: Number
A22: Email | B22: accounts@mercato.com.au | C22: Email
A24: Sites 1
A25: Supply Address | B25: U 2 88 OCONNELL ST NORTH ADELAIDE SA 5006 | D25: Social Medias
A26: Site Owned | B26: TBC | D26: Facebook
A27: Number of Staff Members | D27: Instagram | E27: TBC
A28: Site Surface in M2 | D28: Linkedin | E28: TBC
A29: Site Activity Start Date | D29: Tiktok | E29: TBC
A30: Operation Opening Hours | D30: Snapchat | E30: TBC
A31: Website | D31: Other
A32: © 2024 Environmental Global Benefits

Sheet Airtable Data Sheet
A1: MRIN | B1: Customer Name | C1: Retailer | D1: Invoice Review Period | E1: Invoice Review Number of Days | F1: Site Address: | G1: Total Invoice Cost: | H1: Link to LOA | I1: Bus Name Copy (from Link to LOA) | J1: Trading As | K1: ABN | L1: Postal Address | M1: Telephone | N1: Contact Name | O1: Email | P1: Gas Invoice Rate | Q1: Gas Invoice Usage | R1: Current Supply Charge | S1: New Supply Charge | T1: SME Invoice ex GST | U1: Offer Rate | V1: Contracted Rate: | W1: Monthly Usage | X1: Commission | Y1: Bill Days | Z1: Bill Step 1 Label | AA1: Bill Step 1 MJ | AB1: Bill Step 1 c/MJ | AC1: Bill Step 1 $ | AD1: Bill Step 2 Label | AE1: Bill Step 2 MJ | AF1: Bill Step 2 c/MJ | AG1: Bill Step 2 $ | AH1: Bill Step 3 Label | AI1: Bill Step 3 MJ | AJ1: Bill Step 3 c/MJ | AK1: Bill Step 3 $ | AL1: Bill Step 4 Label | AM1: Bill Step 4 MJ | AN1: Bill Step 4 c/MJ | AO1: Bill Step 4 $ | AP1: Offer S1 Label | AQ1: Offer S1 Days | AR1: Offer S1 Step 1 Band | AS1: Offer S1 Step 1 MJ/day | AT1: Offer S1 Step 1 MJ | AU1: Offer S1 Step 1 c/MJ | AV1: Offer S1 Step 1 $ | AW1: Offer S1 Step 2 Band | AX1: Offer S1 Step 2 MJ/day | AY1: Offer S1 Step 2 MJ | AZ1: Offer S1 Step 2 c/MJ | BA1: Offer S1 Step 2 $ | BB1: Offer S1 Step 3 Band | BC1: Offer S1 Step 3 MJ/day | BD1: Offer S1 Step 3 MJ | BE1: Offer S1 Step 3 c/MJ | BF1: Offer S1 Step 3 $ | BG1: Offer S1 Step 4 Band | BH1: Offer S1 Step 4 MJ/day | BI1: Offer S1 Step 4 MJ | BJ1: Offer S1 Step 4 c/MJ | BK1: Offer S1 Step 4 $ | BL1: Offer S1 Step 5 Band | BM1: Offer S1 Step 5 MJ/day | BN1: Offer S1 Step 5 MJ | BO1: Offer S1 Step 5 c/MJ | BP1: Offer S1 Step 5 $ | BQ1: Offer S2 Label | BR1: Offer S2 Days | BS1: Offer S2 Step 1 Band | BT1: Offer S2 Step 1 MJ/day | BU1: Offer S2 Step 1 MJ | BV1: Offer S2 Step 1 c/MJ | BW1: Offer S2 Step 1 $ | BX1: Offer S2 Step 2 Band | BY1: Offer S2 Step 2 MJ/day | BZ1: Offer S2 Step 2 MJ | CA1: Offer S2 Step 2 c/MJ | CB1: Offer S2 Step 2 $ | CC1: Offer S2 Step 3 Band | CD1: Offer S2 Step 3 MJ/day | CE1: Offer S2 Step 3 MJ | CF1: Offer S2 Step 3 c/MJ | CG1: Offer S2 Step 3 $ | CH1: Offer S2 Step 4 Band | CI1: Offer S2 Step 4 MJ/day | CJ1: Offer S2 Step 4 MJ | CK1: Offer S2 Step 4 c/MJ | CL1: Offer S2 Step 4 $ | CM1: Offer S2 Step 5 Band | CN1: Offer S2 Step 5 MJ/day | CO1: Offer S2 Step 5 MJ | CP1: Offer S2 Step 5 c/MJ | CQ1: Offer S2 Step 5 $

Sheet WIP
A1: ='Member Information Base'!C8
A3: Strategy 2025
A4: Objective | B4: Solution ID | C4: SDG | D4: Solution Group | E4: Solution Description | F4: Est. saving achieved p.a. | G4: Est. revenue achieved p.a. | H4: Est. sav/rev over duration | I4: Est. start date | J4: Priority | K4: Status
B8: (PR) (G-C&I) | C8: 13 | D8: Profile Reset | E8: Gas Commercial & Industrial | F8: ='G-C&I Email Report'!B31 -> #DIV/0! | H8: =F8*3 -> #DIV/0! | I8: Q4 2025 | J8: High | K8: To be confirmed
F22: =F6+F8+F10+F12+F14+F18 -> #DIV/0! | G22: =SUM(G8:G21) -> 0 | H22: =SUM(H6:H21) -> #DIV/0! | I22: Q 2.3.4 2025
A24: *Certain values have been extrapolated based on available data to align with the specific requirements of the solution
A25: *Building upon Mount Pritchard as the baseline, the estimated volume—adjusted according to site size classifications—has been scaled by a factor of 13
A27: © Environmental Global Benefits 2024-25

Sheet Gas Profile
B4: Operating Consumables
B5: Energy | G5: Date
D6: LOA | E6: Letter of Authority | F6: Yes | G6: ='Member Information Base'!F5 -> 46288
D7: EGF | E7: Engagement Form | F7: TBC
A8: Business Name | B8: ='Airtable Data Sheet'!H2 | D8: PSA | E8: Profit Sharing Agreement | F8: ='Member Information Base'!E7 -> Yes
E9: Increase | F9: Value
A10: Site Address: | B10: ='Airtable Data Sheet'!F2 | D10: Contract End date | E10: 46648 | G10: CPI Increase
A11: Supplier | B11: ='Airtable Data Sheet'!C2 | G11: Step Increase
A12: Invoice Review Period | B12: ='Airtable Data Sheet'!D2
A13: Invoice Review Number of Days | B13: ='Airtable Data Sheet'!E2 | C13: Charges from the invoice | G13: Calculated Consumption * Rate
A14: MRIN | B14: ='Airtable Data Sheet'!A2 | C14: Energy Charges ($) | E14: ='Airtable Data Sheet'!P2*'Airtable Data Sheet'!Q2 -> 0 | F14: =E14/E$20 -> 0 | G14: =B15*B16 -> 0
A15: Energy Charge Rate in $/GJ | B15: ='Airtable Data Sheet'!P2 | C15: Transmission Charges ($) | E15: 0 | F15: =E15/E$20 -> 0 | G15: =E15 -> 0
A16: Energy Charge Quantity in GJ | B16: ='Airtable Data Sheet'!Q2 | C16: Distribution Charges ($) | E16: 0 | F16: =E16/E$20 -> 0 | G16: =E16 -> 0
A17: Amount $ (Ex GST) | B17: ='Airtable Data Sheet'!G2 | C17: Regulated Charges ($) | E17: 0 | F17: =E17/E$20 -> 0 | G17: =E17 -> 0
A18: Estimated Yearly Cost | B18: =365*(B17/B13) -> #DIV/0! | C18: Environmental Charges ($) | E18: 0 | F18: =E18/E$20 -> 0 | G18: =E18 -> 0
A19: Contracted Load | C19: Supply Charges ($) - 90 days | E19: 119.59 | F19: =E19/E$20 -> 1 | G19: =E19 -> 119.59
A20: Estimated Load | B20: =IF(N('Airtable Data Sheet'!W2)>0,'Airtable Data Sheet'!W2*12,(B16/B13)*365) | C20: Total | E20: =SUM(E14:E19) -> 119.59 | F20: =SUM(F14:F19) -> 1 | G20: =SUM(G14:G19) -> 119.59
A22: Offer 1
A23: Retailer: | B23: New step pricing (retailer TBC) | C23: Validity: | D23: TBC
B24: Rate $/MJ | C24: Period | D24: Start date | E24: End date | F24: Number of months | G24: Savings:
A25: Period 1 | B25: ='Airtable Data Sheet'!U2 | D25: =IF(C25="", "", DATEVALUE(LEFT(C25, FIND(" to ", C25)-1))) | E25: =IF(C25="", "", DATEVALUE(MID(C25, FIND(" to ", C25)+4, LEN(C25)))) | F25: TBC | G25: ='G Offers Report'!B12 -> #DIV/0!
A26: Period 2 | D26: =IF(C26="", "", DATEVALUE(LEFT(C26, FIND(" to ", C26)-1))) | E26: =IF(C26="", "", DATEVALUE(MID(C26, FIND(" to ", C26)+4, LEN(C26))))
A27: Period 3 | D27: =IF(C27="", "", DATEVALUE(LEFT(C27, FIND(" to ", C27)-1))) | E27: =IF(C27="", "", DATEVALUE(MID(C27, FIND(" to ", C27)+4, LEN(C27))))
A28: Offer 2
A29: Retailer: | B29: Offer 2 | C29: Validity: | D29: =D23 -> TBC | E29: % change | F29: 0.057
B30: Rate $/MJ | C30: Period | D30: Start date | E30: End date | F30: Number of months
A31: Period 1 | B31: =B25*(1+F$29) -> 0 | C31: =IF(C25="","",C25) | D31: =IF(C31="", "", DATEVALUE(LEFT(C31, FIND(" to ", C31)-1))) | E31: =IF(C31="", "", DATEVALUE(MID(C31, FIND(" to ", C31)+4, LEN(C31)))) | F31: =F25 -> TBC
A32: Period 2 | B32: =B26*(1+F$29) -> 0 | C32: =IF(C26="","",C26) | D32: =IF(C32="", "", DATEVALUE(LEFT(C32, FIND(" to ", C32)-1))) | E32: =IF(C32="", "", DATEVALUE(MID(C32, FIND(" to ", C32)+4, LEN(C32)))) | F32: =F26
A33: Period 3 | B33: =B27*(1+F$29) -> 0 | C33: =IF(C27="","",C27) | D33: =IF(C33="", "", DATEVALUE(LEFT(C33, FIND(" to ", C33)-1))) | E33: =IF(C33="", "", DATEVALUE(MID(C33, FIND(" to ", C33)+4, LEN(C33)))) | F33: =F27
A34: Offer 3
A35: Retailer: | B35: Offer 3 | C35: Validity: | D35: =D29 -> TBC | E35: % change | F35: 0.093
B36: Rate $/MJ | C36: Period | D36: Start date | E36: End date | F36: Number of months
A37: Period 1 | B37: =B25*(1+F$35) -> 0 | C37: =IF(C31="","",C31) | D37: =IF(C37="", "", DATEVALUE(LEFT(C37, FIND(" to ", C37)-1))) | E37: =IF(C37="", "", DATEVALUE(MID(C37, FIND(" to ", C37)+4, LEN(C37)))) | F37: =F25 -> TBC
A38: Period 2 | B38: =B26*(1+F$35) -> 0 | C38: =IF(C32="","",C32) | D38: =IF(C38="", "", DATEVALUE(LEFT(C38, FIND(" to ", C38)-1))) | E38: =IF(C38="", "", DATEVALUE(MID(C38, FIND(" to ", C38)+4, LEN(C38)))) | F38: =F26
A39: Period 3 | B39: =B27*(1+F$35) -> 0 | C39: =IF(C33="","",C33) | D39: =IF(C39="", "", DATEVALUE(LEFT(C39, FIND(" to ", C39)-1))) | E39: =IF(C39="", "", DATEVALUE(MID(C39, FIND(" to ", C39)+4, LEN(C39)))) | F39: =F27
A40: © 2024 Environmental Global Benefits

Sheet Gas Comparison Summary
A2: Gas Comparison Energy Cost Summary
A5: ='Member Information Base'!B7
A8: ="Site: "&'Gas Profile'!B10 -> Site: | B8: ="MRIN: "&'Gas Profile'!B14 -> MRIN:
A13: Estimated Year 1 Outcome
A14: =IFERROR(TEXT('G Offers Report'!B12,"$#,##0.00")&" per annum","N/A") -> N/A
A15: =IFERROR(IF('G Offers Report'!B12>0,TEXT('G Offers Report'!B12/'G Offers Report'!G2,"0.0%")&" reduction in estimated annual energy cost",IF('G Offers Report'!B12<0,TEXT(ABS('G Offers Report'!B12)/'G Offers Report'!G2,"0.0%")&" increase in estimated annual energy cost","No material change in estimated annual energy cost")),"N/A") -> N/A
A18: Based on the step pricing and daily supply charge on the current invoice, compared against the proposed offer for the Australian Gas Networks gas network.
A20: Current vs Proposed Gas Cost
A21: Annual Gas Cost | B21: =IFERROR(TEXT('G Offers Report'!J9,"$#,##0.00")&" → "&TEXT('G Offers Report'!J16,"$#,##0.00"),"N/A") -> N/A
A22: Monthly Gas Cost | B22: =IFERROR(TEXT('G Offers Report'!K9,"$#,##0.00")&" → "&TEXT('G Offers Report'!K16,"$#,##0.00"),"N/A") -> N/A
A23: Year 1 Cost Difference | B23: =IFERROR(IF('G Offers Report'!B12>0,TEXT('G Offers Report'!B12,"$#,##0.00")&" saving",IF('G Offers Report'!B12<0,TEXT(ABS('G Offers Report'!B12),"$#,##0.00")&" increase","No material change")),"N/A") -> N/A
A26: Site and Usage
A27: Current Retailer | B27: ='Airtable Data Sheet'!C2
A28: Gas Network | B28: Australian Gas Networks
A29: Estimated Annual Usage | B29: =IFERROR(TEXT('Gas Profile'!B20,"#,##0.00")&" GJ","N/A")
A31: Recommended Next Step
A33: Review and proceed with the engagement form if the preferred offer is accepted, so the new gas agreement can be arranged ahead of the proposed contract start date.
A36: Important Notes
A37: This comparison is based on the retail energy component of the gas invoice. Network charges, environmental charges, regulated charges, metering charges and other pass-through costs may vary over time and are generally outside the fixed retail energy rate.
A39: The proposed gas rates are fixed for each relevant contract period, subject to final retailer acceptance and execution of the required agreement documentation.
A41: ESG (Environmental, Social, and Governance) Impact
A42: GHG Impact: | B42: No material impact identified
A43: Scope Metrics Impact: | B43: Scope 1 (Natural Gas Consumption)
A44: SDG Impact: | B44: SDG 7 - Affordable, reliable, sustainable and modern energy for all
A45: Social Impact: | B45: No material impact identified
A48: © 2026 Carbon Zero Australasia – Environmental Global Benefits

Sheet G C&I Comparison
A1: Gas Comparison
A2: ='Member Information Base'!B7
D3: Cost Comparison Estimated Annual Spend
G4: Current Cost | I4: New Cost
G5: ='G Offers Report'!J9 -> #DIV/0! | I5: ='G Offers Report'!J19 -> $ per year
D9: ='G Offers Report'!C11 -> Number of months | G9: Current Agreement Details:
B10: =K13 -> Offer 2 | C10: Solution represents an annual saving of | E10: =N12-N13 -> #DIV/0! | K10: New Gas Pricing Solution
B11: =K14 -> Offer 1 | C11: Solution represents an annual saving of | E11: =N12-N14 -> #DIV/0! | G11: Average Spend Per Month: | I11: =N12/12 -> #DIV/0! | K11: Retailer | L11: Quantity in GJ: | M11: Price per GJ: | N11: Total Price :
G12: Current Price Rate ($/GJ): | I12: =M12 | K12: ='G Offers Report'!B3 | L12: ='G Offers Report'!D9 -> #DIV/0! | M12: ='G Offers Report'!E9 | N12: =M12*L12 -> #DIV/0!
G13: Estimated Spend Per Annum: | I13: =N12 -> #DIV/0! | K13: ='G Offers Report'!A19 -> Offer 2 | L13: =L12 -> #DIV/0! | M13: ='G Offers Report'!E19 -> $/GJ | N13: =M13*L13 -> #DIV/0!
K14: ='G Offers Report'!A15 -> Offer 1 | L14: =L13 -> #DIV/0! | M14: ='G Offers Report'!E20 -> 2.4 | N14: =M14*L14 -> #DIV/0!
G18: New Agreement Details: Period 1
G20: Average Spend Per Month: | I20: =N13/12 -> #DIV/0!
G21: Offered Price Rate ($/GJ): | I21: =M13 -> $/GJ
G22: Estimated Spend Per Annum: | I22: =N13 -> #DIV/0!
G26: New Agreement Details: Period 1
G28: Average Spend Per Month: | I28: =N14/12 -> #DIV/0!
G29: Offered Price Rate ($/GJ): | I29: =M14 -> 2.4
G30: Estimated Spend Per Annum: | I30: =N14 -> #DIV/0!
F39: ESG Impact Statement
F40: GHG Impact (Co2-e) Impact | H40: None Identified | J40: SCOPE 1
F41: SDG Impact | H41: (SDG-7)
F42: Social Impact | H42: None Identified
A45: © 2025 Environmental Global Benefits

Sheet G Offers Report
A1: Gas Offers Report
A2: ='Member Information Base'!B7 | D2: Estimated Annual Spend | G2: =J9 -> #DIV/0!
A3: Supplier | B3: ='Airtable Data Sheet'!C2 | D3: Offer 1 Estimated Annual Spend | G3: =J16 -> #DIV/0!
A4: Number of sites | B4: 1 | D4: Offer 2 Estimated Annual Spend | G4: =J20 -> #DIV/0!
A5: MIRN | B5: ='Member Information Base'!D9 | D5: Offer 3 Estimated Annual Spend | G5: =J24 -> #DIV/0! | R5: USING CONTRACTED LOAD | S5: USING INVOICE CONSUMPTION
A6: Site address | B6: ='Gas Profile'!B10 | Q6: Annaul into invoice period | R6: Invoice Period Usage
A7: REPORT NO | B7: 40177 | D7: Average | E7: Energy | F7: Transmission | G7: Distribution | H7: Regulated | I7: Environmental | J7: Average | K7: Average
A8: Date of comparison | B8: 46288 | D8: Unit / GJ | E8: $/GJ | F8: % Component | G8: % Component | H8: % Component | I8: % Component | J8: $ Per year | K8: Per Month
A9: Total volume energy (GJ) | B9: ='Gas Profile'!B20 -> #DIV/0! | D9: =B9 -> #DIV/0! | E9: ='Gas Profile'!B15 | F9: Pass Through | G9: Pass Through | H9: Pass Through | I9: Pass Through | J9: =D9*E9+'Airtable Data Sheet'!R2*365 | K9: =J9/12 -> #DIV/0! | M9: =D9*E9 -> #DIV/0! | N9: =M9/365 -> #DIV/0! | O9: =N9*'Gas Profile'!B$13 -> #DIV/0! | P9: =O9-'Gas Profile'!G14 -> #DIV/0! | Q9: =SUM(O9,'Gas Profile'!E$15:E$19) -> #DIV/0! | R9: ='Gas Profile'!G20 -> 119.59 | S9: =Q9-R9 -> #DIV/0!
A10: Contract term (month) | B10: TBC | M10: =#REF!*#REF! -> #REF! | N10: =M10/365 -> #REF! | O10: =N10*'Gas Profile'!B$13 -> #REF! | P10: =O10-'Gas Profile'!G14 -> #REF! | Q10: =SUM(O10,'Gas Profile'!E$15:E$19) -> #REF! | R10: ='Gas Profile'!G20 -> 119.59 | S10: =Q10-R10 -> #REF! | V10: =K9*12 -> #DIV/0!
A11: Estimated Savings: | B11: Annual Savings: | C11: Number of months
A12: =A15 -> Offer 1 | B12: =J9-J16 -> #DIV/0! | C12: 12
A14: Retailers | B14: Validity | C14: TBC | D14: Average | E14: Energy | F14: Transmission | G14: Distribution | H14: Regulated | I14: Environmental | J14: Average | K14: Average
A15: Offer 1 | B15: Start date | C15: End date | D15: GJ per year | E15: $/GJ | F15: % Component | G15: % Component | H15: % Component | I15: % Component | J15: $ per year | K15: $ Per Month | M15: Annaul Contracted Energy Charges | N15: Daily | O15: Invoice Period Energy Charges | P15: Difference Annaulvs Invoice Energy Charges | Q15: Invoice Total Using Yearly | R15: Invoice Total Using Invoice Data | S15: Differences - Using Yearly Vs Monthly Offer | T15: SAVINGS - YEARLY USAGE | U15: SAVINGS - Mnthly USAGE
A16: Period 1 | B16: TBC | C16: TBC | D16: =D9 -> #DIV/0! | E16: ='Gas Profile'!B25 | F16: Pass Through | G16: Pass Through | H16: Pass Through | I16: Pass Through | J16: =D16*E16+'Airtable Data Sheet'!S2*365 | K16: =J16/12 -> #DIV/0! | M16: =D16*E16 -> #DIV/0! | N16: =M16/365 -> #DIV/0! | O16: =N16*'Gas Profile'!B$13 -> #DIV/0! | P16: =O16-'Gas Profile'!$G14 -> #DIV/0! | Q16: =SUM(O16,'Gas Profile'!E$15:E$19) -> #DIV/0! | R16: =SUM('Gas Profile'!E$15:E$19)+('Gas Profile'!B$16*E16) -> 119.59 | S16: =Q16-R16 -> #DIV/0! | T16: =Q$9-Q16 -> #DIV/0! | U16: =R$9-R16 -> 0
M17: =#REF!*#REF! -> #REF! | N17: =M17/365 -> #REF! | O17: =N17*'Gas Profile'!B$13 -> #REF! | P17: =O17-'Gas Profile'!$G16 -> #REF! | Q17: =SUM(O17,'Gas Profile'!E$15:E$19) -> #REF! | R17: =SUM('Gas Profile'!E$15:E$19)+('Gas Profile'!B$16*#REF!) -> #REF! | S17: =Q17-R17 -> #REF! | T17: =Q$9-Q17 -> #DIV/0! | U17: =R$9-R17 -> #REF! | V17: =#REF!*12 -> #REF!
A18: Retailers | B18: Validity | C18: TBC | D18: Average | E18: Energy | F18: Transmission | G18: Distribution | H18: Regulated | I18: Environmental | J18: Average | K18: Average
A19: Offer 2 | B19: Start date | C19: End date | D19: GJ per year | E19: $/GJ | F19: % Component | G19: % Component | H19: % Component | I19: % Component | J19: $ per year | K19: $ Per Month | M19: Annaul Contracted Energy Charges | N19: Daily | O19: Invoice Period Energy Charges | P19: Difference offer vs Invoice Energy Charges | Q19: Invoice Total Using Yearly | R19: Invoice Total Using Invoice Data | S19: Differences - Using Yearly Vs Monthly Offer | T19: SAVINGS - YEARLY USAGE | U19: SAVINGS - Mnthly USAGE
A20: Period 1 | B20: =B16 -> TBC | C20: =C16 -> TBC | D20: =D16 -> #DIV/0! | E20: =E16+2.4 -> 2.4 | F20: =F16 -> Pass Through | G20: =G16 -> Pass Through | H20: =H16 -> Pass Through | I20: =I16 -> Pass Through | J20: =D20*E20 -> #DIV/0! | K20: =J20/12 -> #DIV/0! | M20: =D20*E20 -> #DIV/0! | N20: =M20/365 -> #DIV/0! | O20: =N20*'Gas Profile'!B$13 -> #DIV/0! | P20: =O20-'Gas Profile'!G$14 -> #DIV/0! | Q20: =SUM(O20,'Gas Profile'!E$15:E$19) -> #DIV/0! | R20: =SUM('Gas Profile'!E$15:E$19)+('Gas Profile'!B$16*E20) -> 119.59 | S20: =Q20-R$9 -> #DIV/0! | T20: =Q$9-Q20 -> #DIV/0! | U20: =R$9-R20 -> 0
M21: =#REF!*#REF! -> #REF! | N21: =M21/365 -> #REF! | O21: =N21*'Gas Profile'!B$13 -> #REF! | P21: =O21-'Gas Profile'!G$14 -> #REF! | Q21: =SUM(O21,'Gas Profile'!E$15:E$19) -> #REF! | R21: =SUM('Gas Profile'!E$15:E$19)+('Gas Profile'!B$16*#REF!) -> #REF! | S21: =Q21-R$9 -> #REF! | T21: =Q$9-Q21 -> #DIV/0! | U21: =R$9-R21 -> #REF!
A22: Retailers | B22: Validity | C22: TBC | D22: Average | E22: Energy | F22: Transmission | G22: Distribution | H22: Regulated | I22: Environmental | J22: Average | K22: Average
A23: Offer 3 | B23: Start date | C23: End date | D23: GJ per year | E23: $/GJ | F23: % Component | G23: % Component | H23: % Component | I23: % Component | J23: $ per year | K23: $ Per Month | M23: Annaul Contracted Energy Charges | N23: Daily | O23: Invoice Period Energy Charges | P23: Difference offer vs Invoice Energy Charges | Q23: Invoice Total Using Yearly | R23: Invoice Total Using Invoice Data | S23: Differences - Using Yearly Vs Monthly Offer | T23: SAVINGS - YEARLY USAGE | U23: SAVINGS - Mnthly USAGE
A24: Period 1 | B24: =B20 -> TBC | C24: =C20 -> TBC | D24: =D20 -> #DIV/0! | E24: =E20+1.2 -> 3.6 | F24: =F20 -> Pass Through | G24: =G20 -> Pass Through | H24: =H20 -> Pass Through | I24: =I20 -> Pass Through | J24: =D24*E24 -> #DIV/0! | K24: =J24/12 -> #DIV/0! | M24: =D24*E24 -> #DIV/0! | N24: =M24/365 -> #DIV/0! | O24: =N24*'Gas Profile'!B$13 -> #DIV/0! | P24: =O24-'Gas Profile'!G$14 -> #DIV/0! | Q24: =SUM(O24,'Gas Profile'!E$15:E$19) -> #DIV/0! | R24: =SUM('Gas Profile'!E$15:E$19)+('Gas Profile'!B$16*E24) -> 119.59 | S24: =Q24-R$9 -> #DIV/0! | T24: =Q$9-Q24 -> #DIV/0! | U24: =R$9-R24 -> 0
M25: =#REF!*#REF! -> #REF! | N25: =M25/365 -> #REF! | O25: =N25*'Gas Profile'!B$13 -> #REF! | P25: =O25-'Gas Profile'!G$14 -> #REF! | Q25: =SUM(O25,'Gas Profile'!E$15:E$19) -> #REF! | R25: =SUM('Gas Profile'!E$15:E$19)+('Gas Profile'!B$16*#REF!) -> #REF! | S25: =Q25-R$9 -> #REF! | T25: =Q$9-Q25 -> #DIV/0! | U25: =R$9-R25 -> #REF!
B26: FORNRG PTY LTD // ABN: 40 600 270 620 // data.quote@fornrg.com

Sheet Step Comparison
A1: Gas Step Pricing Comparison
A2: ='Airtable Data Sheet'!B2
A3: ="MRIN: "&'Airtable Data Sheet'!A2&" Site: "&'Airtable Data Sheet'!F2
A5: ="Current bill: "&'Airtable Data Sheet'!C2
A6: =IF('Airtable Data Sheet'!Y2="","","Latest price period on the invoice, "&'Airtable Data Sheet'!Y2&" days")
A7: Step | B7: MJ/day | C7: MJ | D7: c/MJ | E7: Amount
A8: =IF('Airtable Data Sheet'!Z2="","",'Airtable Data Sheet'!Z2) | B8: =IF(OR('Airtable Data Sheet'!AA2="",'Airtable Data Sheet'!Y2=""),"",'Airtable Data Sheet'!AA2/'Airtable Data Sheet'!Y2) | C8: =IF('Airtable Data Sheet'!AA2="","",'Airtable Data Sheet'!AA2) | D8: =IF('Airtable Data Sheet'!AB2="","",'Airtable Data Sheet'!AB2) | E8: =IF('Airtable Data Sheet'!AC2="","",'Airtable Data Sheet'!AC2)
A9: =IF('Airtable Data Sheet'!AD2="","",'Airtable Data Sheet'!AD2) | B9: =IF(OR('Airtable Data Sheet'!AE2="",'Airtable Data Sheet'!Y2=""),"",'Airtable Data Sheet'!AE2/'Airtable Data Sheet'!Y2) | C9: =IF('Airtable Data Sheet'!AE2="","",'Airtable Data Sheet'!AE2) | D9: =IF('Airtable Data Sheet'!AF2="","",'Airtable Data Sheet'!AF2) | E9: =IF('Airtable Data Sheet'!AG2="","",'Airtable Data Sheet'!AG2)
A10: =IF('Airtable Data Sheet'!AH2="","",'Airtable Data Sheet'!AH2) | B10: =IF(OR('Airtable Data Sheet'!AI2="",'Airtable Data Sheet'!Y2=""),"",'Airtable Data Sheet'!AI2/'Airtable Data Sheet'!Y2) | C10: =IF('Airtable Data Sheet'!AI2="","",'Airtable Data Sheet'!AI2) | D10: =IF('Airtable Data Sheet'!AJ2="","",'Airtable Data Sheet'!AJ2) | E10: =IF('Airtable Data Sheet'!AK2="","",'Airtable Data Sheet'!AK2)
A11: =IF('Airtable Data Sheet'!AL2="","",'Airtable Data Sheet'!AL2) | B11: =IF(OR('Airtable Data Sheet'!AM2="",'Airtable Data Sheet'!Y2=""),"",'Airtable Data Sheet'!AM2/'Airtable Data Sheet'!Y2) | C11: =IF('Airtable Data Sheet'!AM2="","",'Airtable Data Sheet'!AM2) | D11: =IF('Airtable Data Sheet'!AN2="","",'Airtable Data Sheet'!AN2) | E11: =IF('Airtable Data Sheet'!AO2="","",'Airtable Data Sheet'!AO2)
A12: Energy | C12: =SUM(C8:C11) | D12: =IFERROR(E12/C12*1000,"") | E12: =SUM(E8:E11)
A14: Proposed offer: Australian Gas Networks gas network
A15: Each step is an MJ per day band, priced for the days in that season.
A16: =IF('Airtable Data Sheet'!AP2="","No offer priced",'Airtable Data Sheet'!AP2&", "&'Airtable Data Sheet'!AQ2&" days")
A17: Band (MJ/day) | B17: MJ/day | C17: MJ | D17: c/MJ | E17: Amount
A18: =IF('Airtable Data Sheet'!AR2="","",'Airtable Data Sheet'!AR2) | B18: =IF('Airtable Data Sheet'!AS2="","",'Airtable Data Sheet'!AS2) | C18: =IF('Airtable Data Sheet'!AT2="","",'Airtable Data Sheet'!AT2) | D18: =IF('Airtable Data Sheet'!AU2="","",'Airtable Data Sheet'!AU2) | E18: =IF('Airtable Data Sheet'!AV2="","",'Airtable Data Sheet'!AV2)
A19: =IF('Airtable Data Sheet'!AW2="","",'Airtable Data Sheet'!AW2) | B19: =IF('Airtable Data Sheet'!AX2="","",'Airtable Data Sheet'!AX2) | C19: =IF('Airtable Data Sheet'!AY2="","",'Airtable Data Sheet'!AY2) | D19: =IF('Airtable Data Sheet'!AZ2="","",'Airtable Data Sheet'!AZ2) | E19: =IF('Airtable Data Sheet'!BA2="","",'Airtable Data Sheet'!BA2)
A20: =IF('Airtable Data Sheet'!BB2="","",'Airtable Data Sheet'!BB2) | B20: =IF('Airtable Data Sheet'!BC2="","",'Airtable Data Sheet'!BC2) | C20: =IF('Airtable Data Sheet'!BD2="","",'Airtable Data Sheet'!BD2) | D20: =IF('Airtable Data Sheet'!BE2="","",'Airtable Data Sheet'!BE2) | E20: =IF('Airtable Data Sheet'!BF2="","",'Airtable Data Sheet'!BF2)
A21: =IF('Airtable Data Sheet'!BG2="","",'Airtable Data Sheet'!BG2) | B21: =IF('Airtable Data Sheet'!BH2="","",'Airtable Data Sheet'!BH2) | C21: =IF('Airtable Data Sheet'!BI2="","",'Airtable Data Sheet'!BI2) | D21: =IF('Airtable Data Sheet'!BJ2="","",'Airtable Data Sheet'!BJ2) | E21: =IF('Airtable Data Sheet'!BK2="","",'Airtable Data Sheet'!BK2)
A22: Energy | C22: =IF(SUM(C18:C21)=0,"",SUM(C18:C21)) | D22: =IFERROR(E22/C22*1000,"") | E22: =IF(SUM(E18:E21)=0,"",SUM(E18:E21))
A24: Annual summary
B25: Current | C25: Proposed | D25: GJ per year | E25: Saving per year
A26: Energy rate | B26: ='Airtable Data Sheet'!P2 | C26: ='Airtable Data Sheet'!U2 | D26: ='Gas Profile'!B20 | E26: =IFERROR(('Airtable Data Sheet'!P2-'Airtable Data Sheet'!U2)*'Gas Profile'!B20,"")
A27: Daily supply | B27: ='Airtable Data Sheet'!R2 | C27: ='Airtable Data Sheet'!S2 | E27: =IFERROR(('Airtable Data Sheet'!R2-'Airtable Data Sheet'!S2)*365,"")
A28: Estimated annual saving | E28: =IFERROR(E26+E27,"")

Sheet G-C&I Engagement Form
A2: Engagement Form Gas Agreement
A3: Service Order Request Date: | C3: 46288
A4: Distributed By: | C4: Environmental Global Benefits
A5: Contact: | C5: EGB Executive
A6: Company Name: | C6: ='Member Information Base'!B7
A7: ACN/ABN: | C7: ='Member Information Base'!B9
A8: Address: | C8: ='Member Information Base'!B10
A9: Tel: | C9: ='Airtable Data Sheet'!M2
A10: Contact Name: | C10: ='Airtable Data Sheet'!N2
A11: Email: | C11: ='Airtable Data Sheet'!O2
A12: Profile Reset
A13: Confidential Disclosure
A14: Contract Type: | C14: Variable Rates Gas
A15: Supplier: | C15: TBC
A16: Number of Sites: | C16: 1
A17: Site Category: | C17: SME to SME
A18: Site Location: | C18: ='Airtable Data Sheet'!F2
A19: Current Pricing: | C19: ='Airtable Data Sheet'!C2&" step pricing, see Step Comparison"
A20: Proposed Offer: | C20: Step pricing on the Australian Gas Networks gas network
A21: Load Flex: | C21: NA
A22: CPA Increase: | C22: NA
A23: ="Distributor Rebate: $"&'Airtable Data Sheet'!X2& " per GJ" -> Distributor Rebate: $ per GJ | C23: Included
A24: Rebate Paid By: | C24: Supplier
A25: MIRN: | C25: ='G Offers Report'!B5
A26: Estimated Annual Outcome: | C26: =IFERROR(TEXT('G Offers Report'!B12,"$#,##0.00")&" per annum","N/A") -> N/A
A27: Next Steps
A28: Members to provide: | C28: Signed Engagement Form
A29: Distributor to organise: | C29: New Agreement
A30: Name: | C30: =C10
A31: Date:
A32: Signature:
A33: 2026-30 © Carbon Zero Australasia

Sheet G-C&I Email Report
A1: Email Template | B1: (PR) (G-C&I)
A3: Subject:
A4: Summary review for: | B4: Gas Commercial & Industrial
A6: Good morning
A7: I hope you are well.
A8: Please find below the summary of our | B8: Gas Commercial & Industrial Summary Report.
A10: MRIN Details: | B10: 55102454015
A15: Current Agreement Details:
A16: Agreement End Date: | B16: 46648
A17: Average Spend Per Month: | B17: ='G Offers Report'!K9 -> #DIV/0! | C17: $/Month
A18: Current Price Rate ($/GJ): | B18: ='G Offers Report'!E9 | C18: $/GJ
A20: New Agreement: Start date: | B20: TBC | C20: ="12 Months" -> 12 Months
A21: Period 1 Rate: | B21: ='G Offers Report'!E16 | C21: =IF(B21="","","$/GJ")
A22: Period 2 Rate: | C22: =IF(B22="","","$/GJ")
A23: Period 3 Rate: | C23: =IF(B23="","","$/GJ")
A25: New Invoice Cost: | B25: $ | C25: $/Month
A26: Period 1: | B26: ='G Offers Report'!K16 -> #DIV/0! | C26: =IF(B26="","","$/Month") -> #DIV/0!
A27: Period 2: | C27: =IF(B27="","","$/Month")
A28: Period 3: | C28: =IF(B28="","","$/Month")
A30: Estimated Savings: | B30: Per Annum
A31: Period 1: | B31: ='G Offers Report'!B12 -> #DIV/0!
A32: Period 2:
A33: Period 3:
A35: Special Condition:
A36: The CPI increase is not applicable to this new offer.
A38: Recommendations:
A39: A 36-Month Term strikes a balance between securing
A40: favourable terms and maintaining flexibility for future
A41: market opportunities or changes in your energy needs.
A43: Please find attached
A44: Gas Commercial & Industrial Summary Report.
A45: Invoice copy for your gas.
A46: Visual Snapshot
... A52: Thank you
